{"doc_id":"5911017","uuid":"","ctitle":"","etitle":"","cdesp":"-","edesp":"","publish_time":"2021-04-16T03:41:55.008Z","lastupdate_time":"","dataset":"{\"data\":[{\"label\":\"2017-18\",\"value\":[\"2.8\"]},{\"label\":\"2018-19\",\"value\":[\"3\"]},{\"label\":\"2019-20\",\"value\":[\"3.2\"]},{\"label\":\"2020-21\",\"value\":[\"\"]}]}","meta":"{\"data\":{\"value\":[null]}}","data_column_names":"{\"data\":{\"label\":\"Year\",\"value\":[\"億\"]}}","settings":"{\"label_data_type\":\"auto\",\"labels\":true,\"legend_mode\":\"off\",\"line_end_labels\":true,\"number_format_secondary.suffix\":\"\"}","thumbnail":"https://public.flourish.studio/published_thumbnails/visualisation/5911017/4b9ac884f27b6bdd.jpg","author":"","tag":"","article":"","meta_addition":""}