{"doc_id":"6960119","uuid":"","ctitle":"20210809_奧運獎牌人口比","etitle":"","cdesp":"20210809_奧運獎牌人口比","edesp":"","publish_time":"2021-08-09T04:06:38.226Z","lastupdate_time":"","dataset":"{\"captions\":[],\"data\":[{\"label\":\"聖馬力諾\",\"values\":[\"1.128666667\"]},{\"label\":\"百慕達\",\"values\":[\"6.392\"]},{\"label\":\"格林納達\",\"values\":[\"10\"]},{\"label\":\"巴哈馬\",\"values\":[\"20\"]},{\"label\":\"新西蘭\",\"values\":[\"24.5\"]},{\"label\":\"牙買加\",\"values\":[\"33.33333333\"]},{\"label\":\"斯洛文尼亞\",\"values\":[\"42\"]},{\"label\":\"斐濟\",\"values\":[\"45\"]},{\"label\":\"荷蘭\",\"values\":[\"47.77777778\"]},{\"label\":\"匈牙利\",\"values\":[\"48\"]},{\"label\":\"格魯吉亞\",\"values\":[\"50\"]},{\"label\":\"克羅地亞\",\"values\":[\"51.25\"]},{\"label\":\"丹麥\",\"values\":[\"52.72727273\"]},{\"label\":\"澳大利亞\",\"values\":[\"56.08695652\"]},{\"label\":\"愛沙尼亞\",\"values\":[\"65\"]},{\"label\":\"瑞士\",\"values\":[\"66.92307692\"]},{\"label\":\"挪威\",\"values\":[\"68.75\"]},{\"label\":\"亞美尼亞\",\"values\":[\"75\"]},{\"label\":\"古巴\",\"values\":[\"75.33333333\"]},{\"label\":\"蒙古\",\"values\":[\"82.5\"]},{\"label\":\"科索沃\",\"values\":[\"88.7689\"]},{\"label\":\"拉脫維亞\",\"values\":[\"95\"]},{\"label\":\"塞爾維亞\",\"values\":[\"96.66666667\"]},{\"label\":\"卡塔爾\",\"values\":[\"96.66666667\"]},{\"label\":\"捷克\",\"values\":[\"97.27272727\"]},{\"label\":\"英國\",\"values\":[\"104.9230769\"]},{\"label\":\"瑞典\",\"values\":[\"113.3333333\"]},{\"label\":\"保加利亞\",\"values\":[\"115\"]},{\"label\":\"愛爾蘭\",\"values\":[\"125\"]},{\"label\":\"中國香港\",\"values\":[\"126.6666667\"]},{\"label\":\"奧地利\",\"values\":[\"128.5714286\"]},{\"label\":\"白俄羅斯\",\"values\":[\"134.2857143\"]},{\"label\":\"斯洛伐克\",\"values\":[\"137.5\"]},{\"label\":\"阿塞拜疆\",\"values\":[\"145.7142857\"]},{\"label\":\"意大利\",\"values\":[\"151\"]},{\"label\":\"加拿大\",\"values\":[\"158.75\"]},{\"label\":\"比利時\",\"values\":[\"165.7142857\"]},{\"label\":\"巴林\",\"values\":[\"170\"]},{\"label\":\"中華台北\",\"values\":[\"195.7292417\"]},{\"label\":\"法國\",\"values\":[\"198.1818182\"]},{\"label\":\"ROC\",\"values\":[\"205.4929577\"]},{\"label\":\"北馬其頓\",\"values\":[\"210\"]},{\"label\":\"日本\",\"values\":[\"217.4137931\"]},{\"label\":\"吉爾吉斯斯坦\",\"values\":[\"220\"]},{\"label\":\"以色列\",\"values\":[\"220\"]},{\"label\":\"多米尼加\",\"values\":[\"220\"]},{\"label\":\"德國\",\"values\":[\"226.7567568\"]},{\"label\":\"烏克蘭\",\"values\":[\"228.9473684\"]},{\"label\":\"哈薩克斯坦\",\"values\":[\"237.5\"]},{\"label\":\"博茨瓦納\",\"values\":[\"240\"]},{\"label\":\"葡萄牙\",\"values\":[\"255\"]},{\"label\":\"韓國\",\"values\":[\"256.5\"]},{\"label\":\"希臘\",\"values\":[\"260\"]},{\"label\":\"納米比亞\",\"values\":[\"260\"]},{\"label\":\"波蘭\",\"values\":[\"270\"]},{\"label\":\"立陶宛\",\"values\":[\"270\"]},{\"label\":\"西班牙\",\"values\":[\"274.7058824\"]},{\"label\":\"芬蘭\",\"values\":[\"275\"]},{\"label\":\"波多黎各\",\"values\":[\"280\"]},{\"label\":\"美國\",\"values\":[\"294.6017699\"]},{\"label\":\"摩爾多瓦\",\"values\":[\"400\"]},{\"label\":\"科威特\",\"values\":[\"430\"]},{\"label\":\"羅馬尼亞\",\"values\":[\"477.5\"]},{\"label\":\"約旦\",\"values\":[\"515\"]},{\"label\":\"肯尼亞\",\"values\":[\"550\"]},{\"label\":\"突尼斯\",\"values\":[\"595\"]},{\"label\":\"厄瓜多爾\",\"values\":[\"596.6666667\"]},{\"label\":\"土庫曼斯坦\",\"values\":[\"610\"]},{\"label\":\"土耳其\",\"values\":[\"653.8461538\"]},{\"label\":\"烏茲別克斯坦\",\"values\":[\"678\"]},{\"label\":\"委內瑞拉\",\"values\":[\"717.5\"]},{\"label\":\"巴西\",\"values\":[\"1019.047619\"]},{\"label\":\"哥倫比亞\",\"values\":[\"1026\"]},{\"label\":\"烏干達\",\"values\":[\"1177.5\"]},{\"label\":\"伊朗\",\"values\":[\"1214.285714\"]},{\"label\":\"阿根廷\",\"values\":[\"1520\"]},{\"label\":\"馬來西亞\",\"values\":[\"1640\"]},{\"label\":\"中國\",\"values\":[\"1641.136364\"]},{\"label\":\"埃及\",\"values\":[\"1738.333333\"]},{\"label\":\"敘利亞\",\"values\":[\"1830\"]},{\"label\":\"南非\",\"values\":[\"2000\"]},{\"label\":\"布基納法索\",\"values\":[\"2150\"]},{\"label\":\"科特迪瓦\",\"values\":[\"2710\"]},{\"label\":\"菲律賓\",\"values\":[\"2775\"]},{\"label\":\"埃塞俄比亞\",\"values\":[\"2947.5\"]},{\"label\":\"加納\",\"values\":[\"3170\"]},{\"label\":\"墨西哥\",\"values\":[\"3257.5\"]},{\"label\":\"泰國\",\"values\":[\"3500\"]},{\"label\":\"沙特阿拉伯\",\"values\":[\"3530\"]},{\"label\":\"摩洛哥\",\"values\":[\"3730\"]},{\"label\":\"印度尼西亞\",\"values\":[\"5528\"]},{\"label\":\"尼日利亞\",\"values\":[\"10570\"]},{\"label\":\"印度\",\"values\":[\"19905.71429\"]}]}","meta":"{\"captions\":{\"from\":{\"type\":\"string\",\"type_id\":\"string$arbitrary_string\",\"output_format_id\":\"string$arbitrary_string\"},\"image\":{\"type\":\"string\",\"type_id\":\"string$arbitrary_string\",\"output_format_id\":\"string$arbitrary_string\"},\"text\":{\"type\":\"string\",\"type_id\":\"string$arbitrary_string\",\"output_format_id\":\"string$arbitrary_string\"},\"to\":{\"type\":\"string\",\"type_id\":\"string$arbitrary_string\",\"output_format_id\":\"string$arbitrary_string\"}},\"data\":{\"label\":{\"type\":\"string\",\"type_id\":\"string$arbitrary_string\",\"output_format_id\":\"string$arbitrary_string\"},\"values\":[{\"type\":\"number\",\"type_id\":\"number$none_point\",\"output_format_id\":\"number$none_point\"}]}}","data_column_names":"{\"captions\":{\"from\":\"From\",\"image\":\"Image\",\"text\":\"Caption\",\"to\":\"To\"},\"data\":{\"label\":\"Country Name\",\"values\":[\"比例\"]}}","settings":"{\"color.categorical_palette\":[\"#66C5CC\",\"#F6CF71\",\"#F89C74\",\"#DCB0F2\",\"#87C55F\",\"#9EB9F3\",\"#FE88B1\",\"#C9DB74\",\"#8BE0A4\",\"#B497E7\",\"#D3B484\",\"#B3B3B3\"],\"counter\":false,\"counter_font_size\":12,\"label_axis_width\":6,\"label_color_in\":null,\"label_mode\":\"axis\",\"layout.header_logo_enabled\":true,\"layout.header_logo_height\":4.5,\"layout.header_logo_src\":\"https://i.imgur.com/IGfOlUB.png\",\"layout.source_label\":\"數據來源：\",\"layout.source_name\":\"olympics.com、聯合國人口基金\",\"layout.subtitle\":\"聖馬力諾僅3萬人口，是次奧運派出5名運動員並收獲3面獎牌\",\"layout.title\":\"歐洲小國聖馬力諾獎牌人口比例最高，每1萬人便有1面獎牌\",\"layout.title_size\":\"2\",\"layout.title_styling\":true,\"sort_ascending\":true,\"totaliser\":false,\"value_format.suffix\":\"萬\"}","thumbnail":"https://public.flourish.studio/published_thumbnails/visualisation/6960119/04023e1782270594.jpg","author":"","tag":"","article":"","meta_addition":""}